setup.py
pyair_utils/__init__.py
pyair_utils/geo.py
pyair_utils/plot.py
pyair_utils/utils.py
pyair_utils.egg-info/PKG-INFO
pyair_utils.egg-info/SOURCES.txt
pyair_utils.egg-info/dependency_links.txt
pyair_utils.egg-info/requires.txt
pyair_utils.egg-info/top_level.txt