Metadata-Version: 1.0
Name: pyair-utils
Version: 3.0.0
Summary: Utilities for the pyair package. Requires the windrose package to work.
Home-page: https://github.com/LionelR/pyair_utils
Author: Lionel Roubeyrie
Author-email: lroubeyrie@limair.asso.fr
License: BSD
Keywords: air quality windrose statistics
Platform: UNKNOWN
